{"nodes": [{"id": "parsers_helm", "label": "helm.py \u2014 Helm chart renderer", "file_type": "code", "source_file": "app/parsers/helm.py", "source_location": null, "source_url": null, "captured_at": null, "author": null, "contributor": null}, {"id": "parsers_helm_render_helm_chart", "label": "render_helm_chart()", "file_type": "code", "source_file": "app/parsers/helm.py", "source_location": "L6-22", "source_url": null, "captured_at": null, "author": null, "contributor": null}], "edges": [{"source": "parsers_helm_render_helm_chart", "target": "parsers_kubernetes_parse_kubernetes_yaml", "relation": "shares_data_with", "confidence": "INFERRED", "confidence_score": 0.85, "source_file": "app/parsers/helm.py", "source_location": null, "weight": 1.0}], "hyperedges": []}